README.md
setup.py
app_stle/__init__.py
app_stle/shockt.py
app_stle.egg-info/PKG-INFO
app_stle.egg-info/SOURCES.txt
app_stle.egg-info/dependency_links.txt
app_stle.egg-info/requires.txt
app_stle.egg-info/top_level.txt
app_stle.egg-info/zip-safe