Metadata-Version: 2.1
Name: app-stle
Version: 0.0.1
Summary: Adaptive pressure profile tracking of the shock-train leading edge.
Home-page: https://gjhunt.github.io/app/
Author: Gregory J. Hunt
Author-email: ghunt@wm.edu
License: GPL3
Platform: UNKNOWN
Classifier: Programming Language :: Python :: 3
Classifier: License :: OSI Approved :: GNU General Public License v3 or later (GPLv3+)
Classifier: Operating System :: OS Independent
Classifier: Topic :: Scientific/Engineering
